pywick/__init__.py
pywick/conditions.py
pywick/constraints.py
pywick/cust_random.py
pywick/custom_regularizers.py
pywick/data_stats.py
pywick/image_utils.py
pywick/initializers.py
pywick/losses.py
pywick/lovasz_losses.py
pywick/metrics.py
pywick/misc.py
pywick/regularizers.py
pywick/samplers.py
pywick/train_classifier.py
pywick/utils.py
pywick/callbacks/CSVLogger.py
pywick/callbacks/Callback.py
pywick/callbacks/CallbackContainer.py
pywick/callbacks/CyclicLRScheduler.py
pywick/callbacks/EarlyStopping.py
pywick/callbacks/ExperimentLogger.py
pywick/callbacks/History.py
pywick/callbacks/LRScheduler.py
pywick/callbacks/LambdaCallback.py
pywick/callbacks/ModelCheckpoint.py
pywick/callbacks/OneCycleLRScheduler.py
pywick/callbacks/ReduceLROnPlateau.py
pywick/callbacks/SimpleModelCheckpoint.py
pywick/callbacks/TQDM.py
pywick/callbacks/__init__.py
pywick/datasets/BaseDataset.py
pywick/datasets/CSVDataset.py
pywick/datasets/ClonedFolderDataset.py
pywick/datasets/FolderDataset.py
pywick/datasets/MultiFolderDataset.py
pywick/datasets/PredictFolderDataset.py
pywick/datasets/TensorDataset.py
pywick/datasets/UsefulDataset.py
pywick/datasets/__init__.py
pywick/datasets/data_utils.py
pywick/datasets/tnt/__init__.py
pywick/datasets/tnt/batchdataset.py
pywick/datasets/tnt/concatdataset.py
pywick/datasets/tnt/dataset.py
pywick/datasets/tnt/listdataset.py
pywick/datasets/tnt/multipartitiondataset.py
pywick/datasets/tnt/resampledataset.py
pywick/datasets/tnt/shuffledataset.py
pywick/datasets/tnt/splitdataset.py
pywick/datasets/tnt/table.py
pywick/datasets/tnt/transform.py
pywick/datasets/tnt/transformdataset.py
pywick/dictmodels/__init__.py
pywick/dictmodels/dict_config.py
pywick/dictmodels/model_spec.py
pywick/functions/__init__.py
pywick/functions/activations_autofn.py
pywick/functions/activations_jit.py
pywick/functions/affine.py
pywick/functions/batchrenorm.py
pywick/functions/cyclicLR.py
pywick/functions/group_norm.py
pywick/functions/mish.py
pywick/functions/swish.py
pywick-0.6.5.dist-info/LICENSE.txt
pywick-0.6.5.dist-info/METADATA
pywick-0.6.5.dist-info/WHEEL
pywick-0.6.5.dist-info/top_level.txt
pywick-0.6.5.dist-info/RECORD
