Metadata-Version: 2.1
Name: pywick
Version: 0.6.5
Summary: High-level batteries-included neural network training library for Pytorch
Home-page: https://github.com/achaiah/pywick
Author: Achaiah
License: UNKNOWN
Download-URL: https://github.com/achaiah/pywick/archive/v0.6.5.tar.gz
Keywords: ai,artificial intelligence,pytorch,classification,deep learning,neural networks,semantic-segmentation,framework
Platform: UNKNOWN
Classifier: Development Status :: 4 - Beta
Classifier: Intended Audience :: Developers
Classifier: License :: OSI Approved :: MIT License
Classifier: Programming Language :: Python :: 3.8
Requires-Dist: albumentations
Requires-Dist: dill
Requires-Dist: h5py
Requires-Dist: numpy
Requires-Dist: opencv-python-headless
Requires-Dist: pandas
Requires-Dist: pillow
Requires-Dist: prodict
Requires-Dist: pycm
Requires-Dist: pyyaml
Requires-Dist: scipy
Requires-Dist: requests
Requires-Dist: scikit-image
Requires-Dist: setuptools
Requires-Dist: six
Requires-Dist: tabulate
Requires-Dist: torch (>=1.6.0)
Requires-Dist: torchvision
Requires-Dist: tqdm
Requires-Dist: yacs
Requires-Dist: wheel
